<?xml version="1.0" encoding="utf-8" ?>
<dwsync>
<file name="nobar_middle.gif" server="sipsam.dyndns.org:22249//srv/www/htdocs/" local="129981613360000000" remote="129981613360000000" />
<file name="redbar_middle.gif" server="sipsam.dyndns.org:22249//srv/www/htdocs/" local="129981613360000000" remote="129981613360000000" />
<file name="nobar_left.gif" server="sipsam.dyndns.org:22249//srv/www/htdocs/" local="129981613360000000" remote="129981613360000000" />
<file name="inf.gif" server="sipsam.dyndns.org:22249//srv/www/htdocs/" local="129981613360000000" remote="129981613360000000" />
<file name="bar_middle.gif" server="sipsam.dyndns.org:22249//srv/www/htdocs/" local="129981613360000000" remote="129981613360000000" />
<file name="bar_right.gif" server="sipsam.dyndns.org:22249//srv/www/htdocs/" local="129981613360000000" remote="129981613360000000" />
<file name="bar_left.gif" server="sipsam.dyndns.org:22249//srv/www/htdocs/" local="129981613360000000" remote="129981613360000000" />
<file name="coinsupg.gif" server="sipsam.dyndns.org:22249//srv/www/htdocs/" local="129981613360000000" remote="129981613360000000" />
<file name="g.gif" server="sipsam.dyndns.org:22249//srv/www/htdocs/" local="129981613360000000" remote="129981613360000000" />
<file name="title_mid.gif" server="sipsam.dyndns.org:22249//srv/www/htdocs/" local="129981613360000000" remote="129981613360000000" />
<file name="fond.gif" server="sipsam.dyndns.org:22249//srv/www/htdocs/" local="129981613360000000" remote="129981613360000000" />
<file name="title_right.gif" server="sipsam.dyndns.org:22249//srv/www/htdocs/" local="129981613360000000" remote="129981613360000000" />
<file name="background.gif" server="sipsam.dyndns.org:22249//srv/www/htdocs/" local="129981613360000000" remote="129981613360000000" />
<file name="coininfg.gif" server="sipsam.dyndns.org:22249//srv/www/htdocs/" local="129981613360000000" remote="129981613360000000" />
<file name="redbar_right.gif" server="sipsam.dyndns.org:22249//srv/www/htdocs/" local="129981613360000000" remote="129981613360000000" />
<file name="space15_15.gif" server="sipsam.dyndns.org:22249//srv/www/htdocs/" local="129981613360000000" remote="129981613360000000" />
<file name="icons.gif" server="sipsam.dyndns.org:22249//srv/www/htdocs/" local="129981613360000000" remote="129981613360000000" />
<file name="redbar_left.gif" server="sipsam.dyndns.org:22249//srv/www/htdocs/" local="129981613360000000" remote="129981613360000000" />
<file name="index.html" server="sipsam.dyndns.org:22249//srv/www/htdocs/" local="129981613360000000" remote="129981613360000000" />
<file name="coininfd.gif" server="sipsam.dyndns.org:22249//srv/www/htdocs/" local="129981613360000000" remote="129981613360000000" />
<file name="nobar_right.gif" server="sipsam.dyndns.org:22249//srv/www/htdocs/" local="129981613360000000" remote="129981613360000000" />
<file name="d.gif" server="sipsam.dyndns.org:22249//srv/www/htdocs/" local="129981613360000000" remote="129981613360000000" />
<file name="sup.gif" server="sipsam.dyndns.org:22249//srv/www/htdocs/" local="129981613360000000" remote="129981613360000000" />
<file name="coinsupd.gif" server="sipsam.dyndns.org:22249//srv/www/htdocs/" local="129981613360000000" remote="129981613360000000" />
<file name="title_left.gif" server="sipsam.dyndns.org:22249//srv/www/htdocs/" local="129981613360000000" remote="129981613360000000" />
</dwsync>